cisco_outshift_agent_utils/__init__.py
cisco_outshift_agent_utils/llm_factory.py
cisco_outshift_agent_utils/logging_config.py
cisco_outshift_agent_utils-0.0.2.dist-info/LICENSE
cisco_outshift_agent_utils-0.0.2.dist-info/METADATA
cisco_outshift_agent_utils-0.0.2.dist-info/WHEEL
cisco_outshift_agent_utils-0.0.2.dist-info/RECORD
